antlr4_verilog/__init__.py
antlr4_verilog/systemverilog/SystemVerilogLexer.py
antlr4_verilog/systemverilog/SystemVerilogParser.py
antlr4_verilog/systemverilog/SystemVerilogParserListener.py
antlr4_verilog/systemverilog/SystemVerilogParserVisitor.py
antlr4_verilog/systemverilog/SystemVerilogPreParser.py
antlr4_verilog/systemverilog/SystemVerilogPreParserListener.py
antlr4_verilog/systemverilog/SystemVerilogPreParserVisitor.py
antlr4_verilog/systemverilog/__init__.py
antlr4_verilog/verilog/VerilogLexer.py
antlr4_verilog/verilog/VerilogParser.py
antlr4_verilog/verilog/VerilogParserListener.py
antlr4_verilog/verilog/VerilogParserVisitor.py
antlr4_verilog/verilog/VerilogPreParser.py
antlr4_verilog/verilog/VerilogPreParserListener.py
antlr4_verilog/verilog/VerilogPreParserVisitor.py
antlr4_verilog/verilog/__init__.py
antlr4_verilog-4.0.0.dist-info/LICENSE
antlr4_verilog-4.0.0.dist-info/METADATA
antlr4_verilog-4.0.0.dist-info/WHEEL
antlr4_verilog-4.0.0.dist-info/top_level.txt
antlr4_verilog-4.0.0.dist-info/RECORD
