Metadata-Version: 2.1
Name: antlr4-verilog
Version: 4.0.0
Summary: Generated files from ANTLR4 for Verilog parsing
Home-page: https://github.com/mtdsousa/antlr4-verilog-python
Author: Marco Diniz Sousa
Author-email: mtdsousa@gmail.com
Project-URL: Bug Tracker, https://github.com/mtdsousa/antlr4-verilog-python/issues
Classifier: Programming Language :: Python :: 3
Classifier: License :: OSI Approved :: MIT License
Classifier: Operating System :: OS Independent
Requires-Python: >=3.6
License-File: LICENSE
Requires-Dist: antlr4-python3-runtime (==4.10)
